tc_messageBroker/__init__.py
tc_messageBroker/message_broker.py
tc_messageBroker/rabbit_mq/__init__.py
tc_messageBroker/rabbit_mq/status.py
tc_messageBroker/rabbit_mq/db_operations/__init__.py
tc_messageBroker/rabbit_mq/db_operations/mongodb.py
tc_messageBroker/rabbit_mq/event/__init__.py
tc_messageBroker/rabbit_mq/event/event.py
tc_messageBroker/rabbit_mq/event/events_microservice.py
tc_messageBroker/rabbit_mq/payload/__init__.py
tc_messageBroker/rabbit_mq/payload/payload.py
tc_messageBroker/rabbit_mq/payload/payload_microservices.py
tc_messageBroker/rabbit_mq/payload/discord_bot/__init__.py
tc_messageBroker/rabbit_mq/payload/discord_bot/chat_input_interaction.py
tc_messageBroker/rabbit_mq/payload/discord_bot/create_followup_message_data.py
tc_messageBroker/rabbit_mq/payload/discord_bot/edit_webhook_data.py
tc_messageBroker/rabbit_mq/payload/discord_bot/interaction_response.py
tc_messageBroker/rabbit_mq/payload/discord_bot/type.py
tc_messageBroker/rabbit_mq/payload/discord_bot/base_types/__init__.py
tc_messageBroker/rabbit_mq/payload/discord_bot/base_types/allowed_mentions.py
tc_messageBroker/rabbit_mq/payload/discord_bot/base_types/attachment.py
tc_messageBroker/rabbit_mq/payload/discord_bot/base_types/embed.py
tc_messageBroker/rabbit_mq/payload/discord_bot/base_types/flags.py
tc_messageBroker/rabbit_mq/payload/discord_bot/base_types/guild.py
tc_messageBroker/rabbit_mq/payload/discord_bot/base_types/interaction_callback_data.py
tc_messageBroker/rabbit_mq/payload/discord_bot/base_types/member.py
tc_messageBroker/rabbit_mq/payload/discord_bot/base_types/user.py
tc_messageBroker/rabbit_mq/queue/__init__.py
tc_messageBroker/rabbit_mq/queue/queue.py
tc_messageBroker/rabbit_mq/saga/__init__.py
tc_messageBroker/rabbit_mq/saga/choreography.py
tc_messageBroker/rabbit_mq/saga/choreography_base.py
tc_messageBroker/rabbit_mq/saga/saga.py
tc_messageBroker/rabbit_mq/saga/saga_base.py
tc_messageBroker/rabbit_mq/saga/transaction_base.py
tc_messageBroker-1.7.1.dist-info/METADATA
tc_messageBroker-1.7.1.dist-info/WHEEL
tc_messageBroker-1.7.1.dist-info/top_level.txt
tc_messageBroker-1.7.1.dist-info/RECORD
