Metadata-Version: 2.1
Name: tc-messageBroker
Version: 1.7.1
Summary: Shared library for message broker in Python
Author: Mohammad Amin Dadgar, RnDAO
Maintainer: Mohammad Amin Dadgar
Maintainer-email: dadgaramin96@gmail.com
Requires-Dist: numpy>=1.24.1
Requires-Dist: pymongo>=4.3.3
Requires-Dist: pytest>=7.2.0
Requires-Dist: ruff>=0.0.265
Requires-Dist: pytest-cov>=4.0.0
Requires-Dist: pytest-asyncio>=0.23.2
Requires-Dist: coverage>=7.2.5
Requires-Dist: pika>=1.3.2
Requires-Dist: jsonschema>=4.17.3
Requires-Dist: python-dotenv>=1.0.0
